zambia_geo/__init__.py
zambia_geo/data.py
zambia_geo/models.py
zambia_geo/scraper.py
zambia_geo/utils.py
zambia_geo/zambia_constituencies.py
zambia_geo/tests/__init__.py
zambia_geo/tests/test_zambia_geo.py
zambia_geo-0.2.0.dist-info/METADATA
zambia_geo-0.2.0.dist-info/WHEEL
zambia_geo-0.2.0.dist-info/top_level.txt
zambia_geo-0.2.0.dist-info/RECORD
