Metadata-Version: 2.4
Name: zambia-geo
Version: 0.2.0
Summary: A Python package containing Zambian provinces, cities, and constituencies data
Home-page: https://github.com/sangwani-coder/zambia-geo
Author: Peter Sangwani Zyambo
Author-email: zyambopeter1@gmail.com
Keywords: zambia,provinces,cities,constituencies,geography
Classifier: Development Status :: 4 - Beta
Classifier: Intended Audience :: Developers
Classifier: Topic :: Software Development :: Libraries :: Python Modules
Classifier: Programming Language :: Python :: 3
Classifier: License :: OSI Approved :: MIT License
Classifier: Operating System :: OS Independent
Requires-Python: >=3.6
Dynamic: author
Dynamic: author-email
Dynamic: classifier
Dynamic: description
Dynamic: description-content-type
Dynamic: home-page
Dynamic: keywords
Dynamic: requires-python
Dynamic: summary
